klogpy/__init__.py
klogpy/cli.py
klogpy/config.py
klogpy/parser.py
klogpy/syntax.py
klogpy-0.1.1.dist-info/entry_points.txt
klogpy-0.1.1.dist-info/WHEEL
klogpy-0.1.1.dist-info/METADATA
klogpy-0.1.1.dist-info/RECORD
