Metadata-Version: 2.1
Name: klogpy
Version: 0.1.1
Summary: Python implementation of klog format for time tracking
License: MIT
Author: Nick Yu
Author-email: nickyu42@gmail.com
Requires-Python: >=3.9,<4.0
Classifier: License :: OSI Approved :: MIT License
Classifier: Programming Language :: Python :: 3
Classifier: Programming Language :: Python :: 3.10
Classifier: Programming Language :: Python :: 3.9
Requires-Dist: click (>=7.1.2,<8.0.0)
Requires-Dist: colorama (>=0.4.4,<0.5.0)
Requires-Dist: parsy (>=1.3,<2.0)
